README.md
setup.cfg
setup.py
mindbody_api/__init__.py
mindbody_api/api_client.py
mindbody_api/configuration.py
mindbody_api/rest.py
mindbody_api.egg-info/PKG-INFO
mindbody_api.egg-info/SOURCES.txt
mindbody_api.egg-info/dependency_links.txt
mindbody_api.egg-info/requires.txt
mindbody_api.egg-info/top_level.txt
mindbody_api/api/__init__.py
mindbody_api/api/appointment_api.py
mindbody_api/api/class_api.py
mindbody_api/api/client_api.py
mindbody_api/api/enrollment_api.py
mindbody_api/api/payroll_api.py
mindbody_api/api/sale_api.py
mindbody_api/api/site_api.py
mindbody_api/api/staff_api.py
mindbody_api/api/user_token_api.py
mindbody_api/models/__init__.py
mindbody_api/models/add_appointment_request.py
mindbody_api/models/add_appointment_response.py
mindbody_api/models/add_arrival_request.py
mindbody_api/models/add_arrival_response.py
mindbody_api/models/add_client_request.py
mindbody_api/models/add_client_response.py
mindbody_api/models/add_client_to_class_request.py
mindbody_api/models/add_client_to_class_response.py
mindbody_api/models/add_client_to_class_visit.py
mindbody_api/models/add_client_to_enrollment_request.py
mindbody_api/models/add_contact_log_request.py
mindbody_api/models/add_contact_log_type.py
mindbody_api/models/amenity.py
mindbody_api/models/appointment.py
mindbody_api/models/appointment_option.py
mindbody_api/models/assigned_client_index.py
mindbody_api/models/autopay_schedule.py
mindbody_api/models/availability.py
mindbody_api/models/booking_window.py
mindbody_api/models/checkout_appointment_booking_request.py
mindbody_api/models/checkout_item.py
mindbody_api/models/checkout_item_wrapper.py
mindbody_api/models/checkout_payment_info.py
mindbody_api/models/checkout_shopping_cart_request.py
mindbody_api/models/class_description.py
mindbody_api/models/class_payroll_event.py
mindbody_api/models/class_schedule.py
mindbody_api/models/client.py
mindbody_api/models/client_contract.py
mindbody_api/models/client_credit_card.py
mindbody_api/models/client_document.py
mindbody_api/models/client_index.py
mindbody_api/models/client_index_value.py
mindbody_api/models/client_membership.py
mindbody_api/models/client_purchase_record.py
