Metadata-Version: 1.1
Name: mindbody-api
Version: 1.0.4
Summary: Mindbody Public API v6 (generated by Swagger Codegen https://github.com/swagger-api/swagger-codegen)
Home-page: https://github.com/mgladki/API-Examples
Author: UNKNOWN
Author-email: mmgladki@gmail.com
License: UNKNOWN
Download-URL: https://github.com/mgladki/API-Examples/archive/1.0.4.tar.gz
Keywords: Swagger,MINDBODY Public API
Platform: UNKNOWN
Classifier: Development Status :: 3 - Alpha
Classifier: Intended Audience :: Developers
Classifier: Topic :: Software Development :: Build Tools
Classifier: License :: OSI Approved :: BSD License
Classifier: Programming Language :: Python :: 3
